MANIFEST.in
README.md
changelog.txt
license.txt
setup.py
GoogleDriveDown/GoogleDriveDown.py
GoogleDriveDown/__iniy__.py
GoogleDriveDown.egg-info/PKG-INFO
GoogleDriveDown.egg-info/SOURCES.txt
GoogleDriveDown.egg-info/dependency_links.txt
GoogleDriveDown.egg-info/not-zip-safe
GoogleDriveDown.egg-info/requires.txt
GoogleDriveDown.egg-info/top_level.txt