Metadata-Version: 2.1
Name: GoogleDriveDown
Version: 0.0.3
Summary: This module allows you to download all the content from a shared google drive url to specified directory.
Home-page: UNKNOWN
Author: Aditya Sisodiya
Author-email: adityasisodiya2803@gmail.com
License: MIT
Keywords: Google Google-Drive
Platform: UNKNOWN
Classifier: Development Status :: 3 - Alpha
Classifier: License :: OSI Approved :: MIT License
Classifier: Programming Language :: Python :: 3.7
Classifier: Topic :: Text Processing :: Linguistic
Classifier: Intended Audience :: Education
Classifier: Operating System :: Microsoft :: Windows :: Windows 10
